cp2kbrew/__init__.py
cp2kbrew/_brewer.py
cp2kbrew/_version.py
cp2kbrew/errors.py
cp2kbrew/handler.py
cp2kbrew/space.py
cp2kbrew/typing.py
cp2kbrew/unit.py
cp2kbrew/utils.py
cp2kbrew/opener/__init__.py
cp2kbrew/opener/log.py
cp2kbrew/opener/trj.py
cp2kbrew/writer/__init__.py
cp2kbrew/writer/base.py
cp2kbrew-0.2.5.dist-info/LICENSE
cp2kbrew-0.2.5.dist-info/METADATA
cp2kbrew-0.2.5.dist-info/WHEEL
cp2kbrew-0.2.5.dist-info/top_level.txt
cp2kbrew-0.2.5.dist-info/RECORD
